[{"inputs":[{"internalType":"address","name":"_tokenFactory","type":"address"}],"stateMutability":"nonpayable","type":"constructor"},{"inputs":[{"internalType":"address","name":"owner","type":"address"}],"name":"OwnableInvalidOwner","type":"error"},{"inputs":[{"internalType":"address","name":"account","type":"address"}],"name":"OwnableUnauthorizedAccount","type":"error"},{"inputs":[],"name":"ReentrancyGuardReentrantCall","type":"error"},{"anonymous":false,"inputs":[{"indexed":false,"internalType":"uint256","name":"marketCapThreshold","type":"uint256"},{"indexed":false,"internalType":"uint256","name":"volumeThreshold","type":"uint256"},{"indexed":false,"internalType":"uint256","name":"holderThreshold","type":"uint256"}],"name":"DefaultGraduationThresholdsUpdated","type":"event"},{"anonymous":false,"inputs":[{"indexed":true,"internalType":"address","name":"token","type":"address"},{"indexed":false,"internalType":"uint256","name":"oldThreshold","type":"uint256"},{"indexed":false,"internalType":"uint256","name":"newThreshold","type":"uint256"}],"name":"GraduationThresholdUpdated","type":"event"},{"anonymous":false,"inputs":[{"indexed":true,"internalType":"address","name":"previousOwner","type":"address"},{"indexed":true,"internalType":"address","name":"newOwner","type":"address"}],"name":"OwnershipTransferred","type":"event"},{"anonymous":false,"inputs":[{"indexed":true,"internalType":"address","name":"token","type":"address"},{"indexed":true,"internalType":"address","name":"creator","type":"address"},{"indexed":false,"internalType":"uint256","name":"finalMarketCap","type":"uint256"},{"indexed":false,"internalType":"address","name":"liquidityPair","type":"address"},{"indexed":false,"internalType":"uint256","name":"timestamp","type":"uint256"}],"name":"TokenGraduated","type":"event"},{"inputs":[],"name":"DEFAULT_GRADUATION_THRESHOLD","outputs":[{"internalType":"uint256","name":"","type":"uint256"}],"stateMutability":"view","type":"function"},{"inputs":[],"name":"MAX_GRADUATION_THRESHOLD","outputs":[{"internalType":"uint256","name":"","type":"uint256"}],"stateMutability":"view","type":"function"},{"inputs":[],"name":"MIN_GRADUATION_THRESHOLD","outputs":[{"internalType":"uint256","name":"","type":"uint256"}],"stateMutability":"view","type":"function"},{"inputs":[],"name":"ethToUsdRate","outputs":[{"internalType":"uint256","name":"","type":"uint256"}],"stateMutability":"view","type":"function"},{"inputs":[{"internalType":"address","name":"tokenAddress","type":"address"}],"name":"getGraduationInfo","outputs":[{"internalType":"bool","name":"isGraduated","type":"bool"},{"internalType":"uint256","name":"thresholdInUSD","type":"uint256"},{"internalType":"uint256","name":"thresholdInETH","type":"uint256"},{"internalType":"uint256","name":"currentMarketCap","type":"uint256"},{"internalType":"bool","name":"readyForGraduation","type":"bool"},{"internalType":"address","name":"liquidityPair","type":"address"}],"stateMutability":"view","type":"function"},{"inputs":[{"internalType":"address","name":"tokenAddress","type":"address"}],"name":"getGraduationThreshold","outputs":[{"internalType":"uint256","name":"","type":"uint256"}],"stateMutability":"view","type":"function"},{"inputs":[{"internalType":"address","name":"token","type":"address"},{"internalType":"address","name":"dexRouter","type":"address"}],"name":"graduateToken","outputs":[{"internalType":"address","name":"liquidityPair","type":"address"}],"stateMutability":"nonpayable","type":"function"},{"inputs":[{"internalType":"address","name":"","type":"address"}],"name":"graduatedPairs","outputs":[{"internalType":"address","name":"","type":"address"}],"stateMutability":"view","type":"function"},{"inputs":[{"internalType":"address","name":"","type":"address"}],"name":"graduatedTokens","outputs":[{"internalType":"bool","name":"","type":"bool"}],"stateMutability":"view","type":"function"},{"inputs":[{"internalType":"address","name":"","type":"address"}],"name":"graduationThreshold","outputs":[{"internalType":"uint256","name":"","type":"uint256"}],"stateMutability":"view","type":"function"},{"inputs":[{"internalType":"address","name":"token","type":"address"}],"name":"isEligibleForGraduation","outputs":[{"internalType":"bool","name":"","type":"bool"}],"stateMutability":"view","type":"function"},{"inputs":[{"internalType":"address","name":"tokenAddress","type":"address"}],"name":"isReadyForGraduation","outputs":[{"internalType":"bool","name":"","type":"bool"}],"stateMutability":"view","type":"function"},{"inputs":[],"name":"owner","outputs":[{"internalType":"address","name":"","type":"address"}],"stateMutability":"view","type":"function"},{"inputs":[],"name":"priceOracle","outputs":[{"internalType":"address","name":"","type":"address"}],"stateMutability":"view","type":"function"},{"inputs":[],"name":"renounceOwnership","outputs":[],"stateMutability":"nonpayable","type":"function"},{"inputs":[{"internalType":"address","name":"tokenAddress","type":"address"},{"internalType":"uint256","name":"thresholdInUSD","type":"uint256"}],"name":"setGraduationThreshold","outputs":[],"stateMutability":"nonpayable","type":"function"},{"inputs":[],"name":"tokenFactory","outputs":[{"internalType":"contract TokenFactory","name":"","type":"address"}],"stateMutability":"view","type":"function"},{"inputs":[{"internalType":"address","name":"newOwner","type":"address"}],"name":"transferOwnership","outputs":[],"stateMutability":"nonpayable","type":"function"},{"inputs":[{"internalType":"uint256","name":"newRate","type":"uint256"}],"name":"updateEthToUsdRate","outputs":[],"stateMutability":"nonpayable","type":"function"},{"inputs":[{"internalType":"uint256","name":"usdAmount","type":"uint256"}],"name":"usdToEth","outputs":[{"internalType":"uint256","name":"","type":"uint256"}],"stateMutability":"view","type":"function"}]